countries_data/__init__.py
countries_data/data/countries/AD.json
countries_data/data/countries/AE.json
countries_data/data/countries/AF.json
countries_data/data/countries/AG.json
countries_data/data/countries/AI.json
countries_data/data/countries/AL.json
countries_data/data/countries/AM.json
countries_data/data/countries/AO.json
countries_data/data/countries/AQ.json
countries_data/data/countries/AR.json
countries_data/data/countries/AS.json
countries_data/data/countries/AT.json
countries_data/data/countries/AU.json
countries_data/data/countries/AW.json
countries_data/data/countries/AX.json
countries_data/data/countries/AZ.json
countries_data/data/countries/BA.json
countries_data/data/countries/BB.json
countries_data/data/countries/BD.json
countries_data/data/countries/BE.json
countries_data/data/countries/BF.json
countries_data/data/countries/BG.json
countries_data/data/countries/BH.json
countries_data/data/countries/BI.json
countries_data/data/countries/BJ.json
countries_data/data/countries/BL.json
countries_data/data/countries/BM.json
countries_data/data/countries/BN.json
countries_data/data/countries/BO.json
countries_data/data/countries/BQ.json
countries_data/data/countries/BR.json
countries_data/data/countries/BS.json
countries_data/data/countries/BT.json
countries_data/data/countries/BV.json
countries_data/data/countries/BW.json
countries_data/data/countries/BY.json
countries_data/data/countries/BZ.json
countries_data/data/countries/CA.json
countries_data/data/countries/CC.json
countries_data/data/countries/CD.json
countries_data/data/countries/CF.json
countries_data/data/countries/CG.json
countries_data/data/countries/CH.json
countries_data/data/countries/CI.json
countries_data/data/countries/CK.json
countries_data/data/countries/CL.json
countries_data/data/countries/CM.json
countries_data/data/countries/CN.json
countries_data/data/countries/CO.json
countries_data/data/countries/CR.json
countries_data/data/countries/CU.json
countries_data-0.1.6.dist-info/LICENSE
countries_data-0.1.6.dist-info/METADATA
countries_data-0.1.6.dist-info/WHEEL
countries_data-0.1.6.dist-info/RECORD
